openactive/__init__.py
openactive/openactive.py
openactive-2.0.0.dist-info/LICENSE
openactive-2.0.0.dist-info/METADATA
openactive-2.0.0.dist-info/WHEEL
openactive-2.0.0.dist-info/top_level.txt
openactive-2.0.0.dist-info/RECORD
