Metadata-Version: 2.1
Name: openactive
Version: 2.0.0
Summary: For reading feeds of sports and activity data published in the OpenActive format
Author-email: Darren Temple <hello@openactive.io>
License: MIT License
Project-URL: Homepage, https://github.com/openactive/openactive-python
Project-URL: Changelog, https://github.com/openactive/openactive-python/blob/main/CHANGELOG.md
Project-URL: Issues, https://github.com/openactive/openactive-python/issues
Keywords: activity,activities,sport,sports
Classifier: Programming Language :: Python :: 3
Classifier: License :: OSI Approved :: MIT License
Classifier: Operating System :: OS Independent
Requires-Python: >=3.6
License-File: LICENSE
Requires-Dist: beautifulsoup4
Requires-Dist: requests
Requires-Dist: termcolor
